{
    "type": "FeatureCollection",
    "crs": {
        "type": "name",
        "properties": {
            "name": "urn:ogc:def:crs:OGC:1.3:CRS84"
        }
    },

    "features": [{
        "type": "Feature",
        "properties": {
            "saleaddres": null,
            "salename": "John Hansen",
            "saleproduc": null,
            "salephone": null,
            "salemail": null,
            "salerating": null
        },
        "geometry": {
            "type": "Point",
            "coordinates": [12.618840997633532, 55.670197754227715]
        }
    }, {
        "type": "Feature",
        "properties": {
            "saleaddres": null,
            "salename": "Niels Jørgensen",
            "saleproduc": "[\"Marmelade\",\"Apple\"]",
            "salephone": "11223344",
            "salemail": "andb@mfs.dk",
            "salerating": 5
        },
        "geometry": {
            "type": "Point",
            "coordinates": [12.660725573656908, 55.622661414512649]
        }
    }, {
        "type": "Feature",
        "properties": {
            "saleaddres": null,
            "salename": "Finn Andersen",
            "saleproduc": "[\"Blomkål\",\"Karftofel\",\"Kirsebær\",\"Kylling\"]",
            "salephone": "66554433",
            "salemail": "js@kff.sl",
            "salerating": 6
        },
        "geometry": {
            "type": "Point",
            "coordinates": [12.585427459457817, 55.625584306226877]
        }
    }]
}
